adutils/__init__.py
adutils-0.6.2.dist-info/LICENSE
adutils-0.6.2.dist-info/WHEEL
adutils-0.6.2.dist-info/METADATA
adutils-0.6.2.dist-info/RECORD
