Metadata-Version: 2.1
Name: adutils
Version: 0.6.2
Summary: Helper and utilities for AppDaemon apps.
Home-page: https://github.com/benleb/adutils
License: MIT
Keywords: ad-apps,appdaemon,app
Author: Ben Lebherz
Author-email: git@benleb.de
Requires-Python: >=3.8
Classifier: Intended Audience :: Developers
Classifier: License :: OSI Approved :: MIT License
Classifier: Operating System :: OS Independent
Classifier: Programming Language :: Python
Classifier: Programming Language :: Python :: 3
Classifier: Programming Language :: Python :: 3.8
Classifier: Programming Language :: Python :: 3.9
Classifier: Topic :: Software Development
Classifier: Topic :: Software Development :: Libraries :: Python Modules
Project-URL: Documentation, https://github.com/benleb/adutils
Project-URL: Repository, https://github.com/benleb/adutils
